djbetty
djbetty/conf
djbetty/templatetags
