Metadata-Version: 1.0
Name: django-betty-cropper
Version: 0.2.3
Summary: A Django app that provides fields for a betty-cropper server
Home-page: https://github.com/theonion/django-betty-cropper
Author: Onion Tech Team
Author-email: tech@theonion.com
License: MIT
Platform: UNKNOWN
